drop_backend/__init__.py
drop_backend/alembic/README
drop_backend/alembic/__init__.py
drop_backend/alembic/env.py
drop_backend/alembic/script.py.mako
drop_backend/alembic/versions/2023_08_22_1134-e306a919aa1d_add_columns_to_parse_events_table.py
drop_backend/alembic/versions/2023_09_22_1853-699d88f31ce6_add_field_column_to_parsed_embedding.py
drop_backend/alembic/versions/2023_09_25_1204-5f3fb0b7e0e1_change_column_name_in_the_parsed_.py
drop_backend/build/webdemo.md
drop_backend/commands/README
drop_backend/commands/__init__.py
drop_backend/commands/__main__.py
drop_backend/commands/embedding_commands.py
drop_backend/commands/geo.py
drop_backend/commands/hoboken_girl_extraction.py
drop_backend/commands/mood_commands.py
drop_backend/commands/webdemo_command_helper.py
drop_backend/lib/__init__.py
drop_backend/lib/ai.py
drop_backend/lib/config_generator.py
drop_backend/lib/db.py
drop_backend/lib/event_node_manager.py
drop_backend/lib/interrogation.py
drop_backend/model/__init__.py
drop_backend/model/ai_conv_types.py
drop_backend/model/merge_base.py
drop_backend/model/mood_model_supervised.py
drop_backend/model/mood_model_unsupervised.py
drop_backend/model/mood_seed.py
drop_backend/model/persistence_model.py
drop_backend/prompts/hoboken_girl_prompt.py
drop_backend/prompts/hoboken_girl_prompt.txt
drop_backend/prompts/mood_prompt.py
drop_backend/types/__init__.py
drop_backend/types/base.py
drop_backend/types/city_event.py
drop_backend/types/custom_types.py
drop_backend/types/mood_submood.py
drop_backend/types/schema/__init__.py
drop_backend/types/schema/city_event_schema.py
drop_backend/types/schema/mood_submood_schema.py
drop_backend/utils/__init__.py
drop_backend/utils/cli_utils.py
drop_backend/utils/color_formatter.py
drop_backend/utils/datetime_utils.py
drop_backend/utils/db_utils.py
drop_backend/utils/extraction_utils.py
drop_backend/utils/formatting.py
drop_backend/utils/ors.py
drop_backend/utils/scraping.py
drop_backend/utils/scratch.py
drop_backend-1.1.2.dist-info/LICENSE
drop_backend-1.1.2.dist-info/METADATA
drop_backend-1.1.2.dist-info/WHEEL
drop_backend-1.1.2.dist-info/RECORD
