Metadata-Version: 2.1
Name: drop-backend
Version: 1.1.2
Summary: API and Command line tools for building drop
Author: Sid
Author-email: itissid@gmail.com
Requires-Python: >=3.10,<4.0
Classifier: Programming Language :: Python :: 3
Classifier: Programming Language :: Python :: 3.10
Classifier: Programming Language :: Python :: 3.11
Provides-Extra: debugging-analysis
Provides-Extra: quality
Requires-Dist: aiofiles (==23.1.0)
Requires-Dist: aiohttp (==3.8.4)
Requires-Dist: aiosignal (==1.3.1)
Requires-Dist: alembic (>=1.11.3,<2.0.0)
Requires-Dist: annotated-types (>=0.6.0,<0.7.0)
Requires-Dist: antlr4-python3-runtime (==4.9.3)
Requires-Dist: appnope (==0.1.3)
Requires-Dist: argon2-cffi (==21.3.0)
Requires-Dist: argon2-cffi-bindings (==21.2.0)
Requires-Dist: arrow (==1.2.3)
Requires-Dist: asgi-csrf (==0.9)
Requires-Dist: asgiref (==3.7.2)
Requires-Dist: asttokens (==2.2.1)
Requires-Dist: async-timeout (==4.0.2)
Requires-Dist: attrs (==23.1.0)
Requires-Dist: backcall (==0.2.0)
Requires-Dist: beautifulsoup4 (==4.12.2)
Requires-Dist: black (==23.3.0)
Requires-Dist: bleach (==6.0.0)
Requires-Dist: blinker (==1.5)
Requires-Dist: braceexpand (==0.1.7)
Requires-Dist: cachetools (==5.3.1)
Requires-Dist: catalogue (==2.0.8)
Requires-Dist: cffi (==1.15.1)
Requires-Dist: cfgv (==3.3.1)
Requires-Dist: charset-normalizer (==3.1.0)
Requires-Dist: click (==8.1.3)
Requires-Dist: click-default-group-wheel (==1.2.2)
Requires-Dist: colorama (==0.4.6)
Requires-Dist: comm (==0.1.3)
Requires-Dist: contexttimer (==0.3.3)
Requires-Dist: cycler (==0.11.0)
Requires-Dist: cymem (==2.0.7)
Requires-Dist: dataclasses-json (==0.5.9)
Requires-Dist: debugpy (==1.6.7)
Requires-Dist: decorator (==5.1.1)
Requires-Dist: defusedxml (==0.7.1)
Requires-Dist: deptry (>=0.12.0,<0.13.0)
Requires-Dist: distlib (==0.3.6)
Requires-Dist: einops (==0.6.1)
Requires-Dist: exceptiongroup (==1.1.1)
Requires-Dist: executing (==1.2.0)
Requires-Dist: fastjsonschema (==2.17.1)
Requires-Dist: filelock (==3.12.0)
Requires-Dist: fonttools (==4.39.4)
Requires-Dist: fqdn (==1.5.1)
Requires-Dist: frozenlist (==1.3.3)
Requires-Dist: fsspec (==2023.5.0)
Requires-Dist: ftfy (==6.1.1)
Requires-Dist: gitdb (==4.0.10)
Requires-Dist: h11 (==0.14.0)
Requires-Dist: h2 (==4.1.0)
Requires-Dist: hpack (==4.0.0)
Requires-Dist: hupper (==1.12)
Requires-Dist: hypercorn (==0.14.3)
Requires-Dist: hyperframe (==6.0.1)
Requires-Dist: icontract (>=2.6.2,<3.0.0) ; extra == "debugging-analysis"
Requires-Dist: identify (==2.5.24)
Requires-Dist: idna (==3.4)
Requires-Dist: importlib-metadata (==6.6.0)
Requires-Dist: iniconfig (==2.0.0)
Requires-Dist: install (==1.3.5)
Requires-Dist: iopath (==0.1.10)
Requires-Dist: ipdb (>=0.13,<0.14) ; extra == "debugging-analysis"
Requires-Dist: ipykernel (==6.23.1) ; extra == "debugging-analysis"
Requires-Dist: ipython-genutils (==0.2.0) ; extra == "debugging-analysis"
Requires-Dist: ipywidgets (==8.0.6) ; extra == "debugging-analysis"
Requires-Dist: isoduration (==20.11.0)
Requires-Dist: itsdangerous (==2.1.2)
Requires-Dist: janus (==1.0.0)
Requires-Dist: jedi (==0.18.2)
Requires-Dist: jsonpath-ng (==1.5.3)
Requires-Dist: jsonpointer (==2.3)
Requires-Dist: jsonschema (==4.17.3)
Requires-Dist: langcodes (==3.3.0)
Requires-Dist: lazy-loader (==0.2)
Requires-Dist: markdown-it-py (==2.2.0)
Requires-Dist: markupsafe (==2.1.2)
Requires-Dist: marshmallow (==3.19.0)
Requires-Dist: marshmallow-enum (==1.5.1)
Requires-Dist: matplotlib-inline (==0.1.6)
Requires-Dist: mdurl (==0.1.2)
Requires-Dist: mergedeep (==1.3.4)
Requires-Dist: mistune (==2.0.5)
Requires-Dist: mpmath (==1.3.0)
Requires-Dist: multidict (==6.0.4)
Requires-Dist: murmurhash (==1.0.9)
Requires-Dist: mypy (>=1.6.1,<2.0.0) ; extra == "quality"
Requires-Dist: mypy-extensions (==1.0.0)
Requires-Dist: nest-asyncio (==1.5.6)
Requires-Dist: networkx (==3.1)
Requires-Dist: nodeenv (==1.8.0)
Requires-Dist: openai (==0.27.7)
Requires-Dist: packaging (==22.0)
Requires-Dist: pandocfilters (==1.5.0)
Requires-Dist: parso (==0.8.3)
Requires-Dist: pathspec (==0.11.1)
Requires-Dist: pathy (==0.10.1)
Requires-Dist: pexpect (==4.8.0)
Requires-Dist: pickleshare (==0.7.5)
Requires-Dist: pillow (==9.5.0)
Requires-Dist: platformdirs (==3.5.1)
Requires-Dist: pluggy (==1.2.0)
Requires-Dist: ply (==3.11)
Requires-Dist: portalocker (==2.7.0)
Requires-Dist: priority (==2.0.0)
Requires-Dist: prometheus-client (==0.16.0)
Requires-Dist: prompt-toolkit (==3.0.38)
Requires-Dist: protobuf (==4.23.2)
Requires-Dist: psutil (==5.9.5)
Requires-Dist: ptyprocess (==0.7.0)
Requires-Dist: pure-eval (==0.2.2)
Requires-Dist: pycparser (==2.21)
Requires-Dist: pydantic[mypy] (>=2.3.0,<3.0.0)
Requires-Dist: pygeoif (>=1.1.1,<2.0.0)
Requires-Dist: pygments (==2.15.1)
Requires-Dist: pylance (==0.5.4) ; extra == "quality"
Requires-Dist: pylint (>=2.17.5,<3.0.0) ; extra == "quality"
Requires-Dist: pympler (==1.0.1)
Requires-Dist: pyparsing (==3.0.9)
Requires-Dist: pyrsistent (==0.19.3)
Requires-Dist: pytest (==7.4.0)
Requires-Dist: python-dateutil (==2.8.2)
Requires-Dist: python-dotenv (>=1.0.0,<2.0.0)
Requires-Dist: python-json-logger (==2.0.7)
Requires-Dist: python-magic (==0.4.27)
Requires-Dist: python-multipart (==0.0.6)
Requires-Dist: python-slugify (==8.0.1)
Requires-Dist: pytz (==2023.3)
Requires-Dist: pytz-deprecation-shim (==0.1.0.post0)
Requires-Dist: pyzmq (==25.0.2)
Requires-Dist: qtpy (==2.3.1)
Requires-Dist: quart (==0.18.4)
Requires-Dist: quart-cors (==0.6.0)
Requires-Dist: regex (==2023.5.5)
Requires-Dist: requests (==2.31.0)
Requires-Dist: rfc3339-validator (==0.1.4)
Requires-Dist: rfc3986-validator (==0.1.1)
Requires-Dist: rich (==13.4.1)
Requires-Dist: send2trash (==1.8.2)
Requires-Dist: sentencepiece (==0.1.99)
Requires-Dist: six (==1.16.0)
Requires-Dist: smart-open (==6.3.0)
Requires-Dist: smmap (==5.0.0)
Requires-Dist: sniffio (==1.3.0)
Requires-Dist: soupsieve (==2.4.1)
Requires-Dist: spacy-legacy (==3.0.12)
Requires-Dist: spacy-loggers (==1.0.4)
Requires-Dist: sqlalchemy (==2.0.18)
Requires-Dist: sqlalchemy-utils (==0.41.1)
Requires-Dist: sqlite-fts4 (==1.0.3)
Requires-Dist: sqlite-utils (==3.33)
Requires-Dist: stack-data (==0.6.2)
Requires-Dist: sympy (==1.12)
Requires-Dist: tabulate (==0.9.0)
Requires-Dist: tenacity (==8.2.2)
Requires-Dist: terminado (==0.17.1)
Requires-Dist: text-unidecode (==1.3)
Requires-Dist: time-uuid (>=0.2.0,<0.3.0)
Requires-Dist: tinycss2 (==1.2.1)
Requires-Dist: toml (==0.10.2)
Requires-Dist: tomli (==2.0.1)
Requires-Dist: tornado (==6.3.2)
Requires-Dist: tqdm (==4.65.0)
Requires-Dist: traitlets (==5.9.0)
Requires-Dist: typer (>=0.9.0,<0.10.0)
Requires-Dist: types-requests (==2.31.0.1)
Requires-Dist: types-urllib3 (==1.26.25.13)
Requires-Dist: typing-extensions (==4.6.3)
Requires-Dist: typing-inspect (==0.9.0)
Requires-Dist: tzdata (==2023.3)
Requires-Dist: tzlocal (==4.3)
Requires-Dist: uri-template (==1.2.0)
Requires-Dist: urllib3 (==2.0.2)
Requires-Dist: validators (==0.20.0)
Requires-Dist: wasabi (==1.1.2)
Requires-Dist: wcwidth (==0.2.6)
Requires-Dist: webcolors (==1.13)
Requires-Dist: webencodings (==0.5.1)
Requires-Dist: websocket-client (==1.5.2)
Requires-Dist: werkzeug (==2.3.4)
Requires-Dist: wsproto (==1.2.0)
Requires-Dist: yarl (==1.9.2)
Requires-Dist: zipp (==3.15.0)
